{
  "status": "0",
  "msg": "",
  "result": [
    {
      "productId": "100001",
      "productName": "小米3",
      "salePrice": "2499",
      "productImage": "1.jpg"
    },
    {
      "productId": "100001",
      "productName": "小米4",
      "salePrice": "2399",
      "productImage": "2.jpg"
    },
    {
      "productId": "100001",
      "productName": "小米5",
      "salePrice": "2699",
      "productImage": "6.jpg"
    },
    {
      "productId": "100001",
      "productName": "小米6",
      "salePrice": "2199",
      "productImage": "4.jpg"
    },
    {
      "productId": "100001",
      "productName": "xxx",
      "salePrice": "1200",
      "productImage": "7.jpg"
    },
    {
      "productId": "100001",
      "productName": "yyy",
      "salePrice": "595",
      "productImage": "8.jpg"
    },
    {
      "productId": "100001",
      "productName": "yyy",
      "salePrice": "787",
      "productImage": "9.jpg"
    },
    {
      "productId": "100001",
      "productName": "yyy",
      "salePrice": "2345",
      "productImage": "10.jpg"
    },
    {
      "productId": "100001",
      "productName": "zzz",
      "salePrice": "2567",
      "productImage": "11.jpg"
    },
    {
      "productId": "100001",
      "productName": "vvv",
      "salePrice": "2842",
      "productImage": "12.jpg"
    },
    {
      "productId": "100001",
      "productName": "uuu",
      "salePrice": "2991",
      "productImage": "13.jpg"
    },
    {
      "productId": "100001",
      "productName": "jjj",
      "salePrice": "2471",
      "productImage": "14.jpg"
    },
    {
      "productId": "100001",
      "productName": "yyy",
      "salePrice": "1234",
      "productImage": "http://pic6.huitu.com/res/20130116/84481_20130116142820494200_1.jpg"
    },
    {
      "productId": "100001",
      "productName": "yyy",
      "salePrice": "3835",
      "productImage": "http://img2.imgtn.bdimg.com/it/u=4289577871,2613521315&fm=11&gp=0.jpg"
    }
  ]
}
